setup.py
lib/JumpScale/__init__.py
lib/JumpScale/base/BYTEPROCESSOR.py
lib/JumpScale/base/ERRORHANDLER.py
lib/JumpScale/base/FS.py
lib/JumpScale/base/FSWALKER.py
lib/JumpScale/base/FSWALKER_test.py
lib/JumpScale/base/LOADER.py
lib/JumpScale/base/REGEXTOOL.py
lib/JumpScale/base/TIMER.py
lib/JumpScale/base/__init__.py
lib/JumpScale/baselib/__init__.py
lib/JumpScale/baselib/actions/__init__.py
lib/JumpScale/baselib/actions/action/ActionController.py
lib/JumpScale/baselib/actions/action/RunningAction.py
lib/JumpScale/baselib/actions/action/__init__.py
lib/JumpScale/baselib/actions/transaction/Transaction.py
lib/JumpScale/baselib/actions/transaction/TransactionController.py
lib/JumpScale/baselib/actions/transaction/__init__.py
lib/JumpScale/baselib/bitbucket/Bitbucket.py
lib/JumpScale/baselib/bitbucket/BitbucketConfigManagement.py
lib/JumpScale/baselib/bitbucket/BitbucketInterface.py
lib/JumpScale/baselib/bitbucket/__init__.py
lib/JumpScale/baselib/blobstor/BlobStor.py
lib/JumpScale/baselib/blobstor/BlobStorConfigManagement.py
lib/JumpScale/baselib/blobstor/__init__.py
lib/JumpScale/baselib/cloudsystemfs/CifsFS.py
lib/JumpScale/baselib/cloudsystemfs/CloudSystemFS.py
lib/JumpScale/baselib/cloudsystemfs/FileFS.py
lib/JumpScale/baselib/cloudsystemfs/FtpFS.py
lib/JumpScale/baselib/cloudsystemfs/HttpFS.py
lib/JumpScale/baselib/cloudsystemfs/SshFS.py
lib/JumpScale/baselib/cloudsystemfs/__init__.py
lib/JumpScale/baselib/cmdline/CommandLauncher.py
lib/JumpScale/baselib/cmdline/Options.py
lib/JumpScale/baselib/cmdline/__init__.py
lib/JumpScale/baselib/cmdutils/__init__.py
lib/JumpScale/baselib/code/Appserver6GreenletBase.py
lib/JumpScale/baselib/code/Appserver6GreenletScheduleBase.py
lib/JumpScale/baselib/code/Appserver6GreenletTaskletsBase.py
lib/JumpScale/baselib/code/ClassBase.py
lib/JumpScale/baselib/code/Code.py
lib/JumpScale/baselib/code/__init__.py
lib/JumpScale/baselib/codeexecutor/CodeExecutor.py
lib/JumpScale/baselib/codeexecutor/__init__.py
lib/JumpScale_core.egg-info/PKG-INFO
lib/JumpScale_core.egg-info/SOURCES.txt
lib/JumpScale_core.egg-info/dependency_links.txt
lib/JumpScale_core.egg-info/top_level.txt
