Metadata-Version: 1.1
Name: JumpScale-core
Version: 6.0.0
Summary: Python Automation framework
Home-page: http://www.jumpscale.org
Author: JumpScale
Author-email: info@jumpscale.org
License: FreeBSD
Download-URL: http://pypi.python.org/pypi/JumpScale/
Platform: UNKNOWN
Classifier: Intended Audience :: Developers
Classifier: Operating System :: OS Independent
Classifier: Programming Language :: Python
Classifier: License :: OSI Approved :: BSD License
